rwth_nb/__init__.py
rwth_nb/misc/__init__.py
rwth_nb/misc/feedback.py
rwth_nb/misc/filters.py
rwth_nb/misc/media.py
rwth_nb/misc/notebook.py
rwth_nb/misc/share.py
rwth_nb/misc/signals.py
rwth_nb/misc/submission.py
rwth_nb/misc/transforms.py
rwth_nb/plots/__init__.py
rwth_nb/plots/colors.py
rwth_nb/plots/mpl_decorations.py
rwth_nb-0.1.9.dist-info/LICENSE
rwth_nb-0.1.9.dist-info/METADATA
rwth_nb-0.1.9.dist-info/WHEEL
rwth_nb-0.1.9.dist-info/top_level.txt
rwth_nb-0.1.9.dist-info/RECORD
