Metadata-Version: 2.2
Name: rwth_nb
Version: 0.1.9
Summary: RWTH Python Library for Jupyter Notebooks
Home-page: https://git.rwth-aachen.de/jupyter/rwth-nb
Author: Christian Rohlfing, Lars Thieling, Christoph Weyer, Jens Schneider, Steffen Vogel
Author-email: rohlfing@ient.rwth-aachen.de
License: MIT
License-File: LICENSE
Dynamic: author
Dynamic: author-email
Dynamic: description
Dynamic: description-content-type
Dynamic: home-page
Dynamic: license
Dynamic: summary
